aquarius_webportal/__init__.py
aquarius_webportal/main.py
aquarius_webportal-0.4.1.dist-info/licenses/LICENSE
aquarius_webportal-0.4.1.dist-info/METADATA
aquarius_webportal-0.4.1.dist-info/WHEEL
aquarius_webportal-0.4.1.dist-info/top_level.txt
aquarius_webportal-0.4.1.dist-info/RECORD
