Metadata-Version: 2.4
Name: aquarius_webportal
Version: 0.4.1
Summary: Python code to get data from implementations of Aquarius Web Portal
Home-page: https://github.com/kinverarity1/aquarius_webportal
Author: Kent Inverarity
Author-email: kinverarity@hotmail.com
License: MIT
Keywords: python groundwater data-access surface-water
Classifier: Programming Language :: Python :: 3
Classifier: Topic :: Scientific/Engineering
License-File: LICENSE
Requires-Dist: requests
Requires-Dist: pandas>=0.24.1
Requires-Dist: lxml
Dynamic: author
Dynamic: author-email
Dynamic: classifier
Dynamic: description
Dynamic: description-content-type
Dynamic: home-page
Dynamic: keywords
Dynamic: license
Dynamic: license-file
Dynamic: requires-dist
Dynamic: summary
